creator/__init__.py
creator/help.py
creator/input.py
creator/paginator.py
creator/embed_creator/__init__.py
creator/embed_creator/methods.py
embedcreator-0.1.9.dist-info/LICENSE
embedcreator-0.1.9.dist-info/METADATA
embedcreator-0.1.9.dist-info/WHEEL
embedcreator-0.1.9.dist-info/top_level.txt
embedcreator-0.1.9.dist-info/RECORD
