Metadata-Version: 2.1
Name: embedcreator
Version: 0.1.9
Author: Leticia Sousa
Author-email: leticialimasousa2007@gmail.com
License: MIT License
License-File: LICENSE
Requires-Dist: discord.py
